README.md
setup.py
flatpakdev/__init__.py
flatpakdev/__main__.py
flatpakdev/flatpakdev.py
flatpakdev.egg-info/PKG-INFO
flatpakdev.egg-info/SOURCES.txt
flatpakdev.egg-info/dependency_links.txt
flatpakdev.egg-info/entry_points.txt
flatpakdev.egg-info/top_level.txt