Metadata-Version: 1.0
Name: flatpakdev
Version: 0.1
Summary: Python command line tool that wrapps Flatpak-Builder
Home-page: https://github.com/kevinlopezandrade/FlatpakDev
Author: Kevin Lopez Andrade
Author-email: kevin@kevlopez.com
License: UNKNOWN
Platform: UNKNOWN
